{
  "project_info": {
    "project_number": "560877364974",
    "project_id": "mystock-admin",
    "storage_bucket": "mystock-admin.appspot.com"
  },
  "client": [
    {
      "client_info": {
        "mobilesdk_app_id": "1:560877364974:android:662c952d346f163c0275ff",
        "android_client_info": {
          "package_name": "com.example.mystock"
        }
      },
      "oauth_client": [],
      "api_key": [
        {
          "current_key": "AIzaSyDRXhlCwuOllWNfSIDBMiIWt4x82qW6Zzw"
        }
      ],
      "services": {
        "appinvite_service": {
          "other_platform_oauth_client": []
        }
      }
    }
  ],
  "configuration_version": "1"
}